stochpw/__init__.py
stochpw/core.py
stochpw/data.py
stochpw/diagnostics/__init__.py
stochpw/diagnostics/advanced.py
stochpw/diagnostics/balance.py
stochpw/diagnostics/weights.py
stochpw/models/__init__.py
stochpw/models/base.py
stochpw/models/linear.py
stochpw/models/mlp.py
stochpw/plotting.py
stochpw/training/__init__.py
stochpw/training/batch.py
stochpw/training/loop.py
stochpw/training/losses.py
stochpw/training/regularization.py
stochpw/utils.py
stochpw/weights.py
stochpw-0.3.0.dist-info/LICENSE
stochpw-0.3.0.dist-info/METADATA
stochpw-0.3.0.dist-info/WHEEL
stochpw-0.3.0.dist-info/RECORD
