Metadata-Version: 2.3
Name: stochpw
Version: 0.3.0
Summary: Stochastic gradient descent implementation of permutation weighting
License: Apache-2.0
Author: Drew Dimmery
Author-email: pypi@ddimmery.com
Requires-Python: >=3.12,<4.0
Classifier: License :: OSI Approved :: Apache Software License
Classifier: Programming Language :: Python :: 3
Classifier: Programming Language :: Python :: 3.12
Classifier: Programming Language :: Python :: 3.13
Requires-Dist: jax (>=0.4.0,<0.5.0)
Requires-Dist: jaxlib (>=0.4.0,<0.5.0)
Requires-Dist: numpy (>=1.26.0,<2.0.0)
Requires-Dist: numpyro (>=0.15.0,<0.16.0)
Requires-Dist: optax (>=0.2.0,<0.3.0)
Requires-Dist: plotnine (>=0.15.0,<0.16.0)
Project-URL: Homepage, https://github.com/ddimmery/stochpw
Project-URL: Repository, https://github.com/ddimmery/stochpw
